README.rst
setup.cfg
setup.py
link/__init__.py
link.wsgi.egg-info/PKG-INFO
link.wsgi.egg-info/SOURCES.txt
link.wsgi.egg-info/dependency_links.txt
link.wsgi.egg-info/requires.txt
link.wsgi.egg-info/top_level.txt
link/wsgi/__init__.py
link/wsgi/app.py
link/wsgi/middleware.py
link/wsgi/req.py
link/wsgi/resp.py
link/wsgi/router.py
link/wsgi/url.py