Metadata-Version: 1.0
Name: link.wsgi
Version: 0.2
Summary: WSGI micro-framework
Home-page: https://github.com/linkdd/link.wsgi
Author: David Delassus
Author-email: david.jose.delassus@gmail.com
License: MIT
Keywords: wsgi microframework
Platform: UNKNOWN
